{
  "@microsoft/generator-sharepoint": {
    "plusBeta": false,
    "isCreatingSolution": true,
    "nodeVersion": "22.14.0",
    "sdksVersions": {
      "@microsoft/microsoft-graph-client": "3.0.2",
      "@microsoft/teams-js": "2.24.0"
    },
    "version": "1.21.1",
    "libraryName": "spfx-teamslink",
    "libraryId": "5f81c107-6362-4582-901d-53a0278eb9f7",
    "environment": "spo",
    "packageManager": "npm",
    "solutionName": "spfx-teamslink",
    "solutionShortDescription": "spfx-teamslink description",
    "skipFeatureDeployment": true,
    "isDomainIsolated": false,
    "componentType": "extension",
    "extensionType": "ApplicationCustomizer"
  }
}